{
  "additionalNames": "Lower, Lower one's eyes",
  "albums": [
    {
      "artistString": "ぬゆり feat. v4 flower",
      "createDate": "2021-11-10T05:11:23.37",
      "defaultName": "ロウワー",
      "defaultNameLanguage": "Japanese",
      "discType": "Single",
      "id": 31201,
      "name": "ロウワー",
      "ratingAverage": 5.0,
      "ratingCount": 1,
      "releaseDate": { "day": 9, "isEmpty": false, "month": 11, "year": 2021 },
      "status": "Finished",
      "version": 4
    },
    {
      "artistString": "ぬゆり, 和田たけあき feat. various",
      "catalogNumber": "AZNT-70",
      "createDate": "2022-12-21T06:17:16.103",
      "defaultName": "ULTRAPANIC2",
      "defaultNameLanguage": "English",
      "discType": "Album",
      "id": 34396,
      "name": "ULTRAPANIC2",
      "ratingAverage": 5.0,
      "ratingCount": 4,
      "releaseDate": { "day": 3, "isEmpty": false, "month": 3, "year": 2023 },
      "status": "Finished",
      "version": 21
    }
  ],
  "alternateVersions": [
    {
      "artistString": "ぬゆり feat. various",
      "createDate": "2021-11-10T05:26:03.817",
      "defaultName": "ロウワー",
      "defaultNameLanguage": "Japanese",
      "favoritedTimes": 7,
      "id": 365111,
      "lengthSeconds": 233,
      "name": "ロウワー",
      "originalVersionId": 365108,
      "publishDate": "2021-10-31T00:00:00Z",
      "pvServices": "NicoNicoDouga, Youtube",
      "ratingScore": 39,
      "songType": "Cover",
      "status": "Finished",
      "version": 6
    },
    {
      "artistString": "ぬゆり feat. 初音ミク",
      "createDate": "2022-05-02T23:26:05.777",
      "defaultName": "ロウワー",
      "defaultNameLanguage": "Japanese",
      "favoritedTimes": 3,
      "id": 404790,
      "lengthSeconds": 107,
      "name": "ロウワー",
      "originalVersionId": 365108,
      "publishDate": "2021-10-31T00:00:00Z",
      "pvServices": "Youtube",
      "ratingScore": 13,
      "songType": "Cover",
      "status": "Finished",
      "version": 8
    },
    {
      "artistString": "tsumugilovemail feat. various",
      "createDate": "2021-12-19T19:59:14.923",
      "defaultName": "ロウワー",
      "defaultNameLanguage": "Japanese",
      "favoritedTimes": 2,
      "id": 372220,
      "lengthSeconds": 231,
      "name": "ロウワー",
      "originalVersionId": 365108,
      "publishDate": "2021-11-11T00:00:00Z",
      "pvServices": "Youtube",
      "ratingScore": 6,
      "songType": "Cover",
      "status": "Finished",
      "version": 2
    },
    {
      "artistString": "Hye feat. 喜楽あゆみ",
      "createDate": "2022-03-21T12:19:57.007",
      "defaultName": "ロウワー",
      "defaultNameLanguage": "Japanese",
      "favoritedTimes": 0,
      "id": 393778,
      "lengthSeconds": 231,
      "name": "ロウワー",
      "originalVersionId": 365108,
      "publishDate": "2021-11-11T00:00:00Z",
      "pvServices": "Youtube, SoundCloud",
      "ratingScore": 0,
      "songType": "Cover",
      "status": "Finished",
      "version": 4
    },
    {
      "artistString": "macaron feat. KAITO V3 (Straight)",
      "createDate": "2024-02-20T19:06:13.613",
      "defaultName": "ロウワー",
      "defaultNameLanguage": "Japanese",
      "favoritedTimes": 0,
      "id": 588040,
      "lengthSeconds": 230,
      "name": "ロウワー",
      "originalVersionId": 365108,
      "publishDate": "2021-11-16T00:00:00Z",
      "pvServices": "NicoNicoDouga, Youtube",
      "ratingScore": 0,
      "songType": "Cover",
      "status": "Finished",
      "version": 4
    },
    {
      "artistString": "ImaiP feat. 巡音ルカ",
      "createDate": "2021-11-20T07:22:38.05",
      "defaultName": "ロウワー",
      "defaultNameLanguage": "Japanese",
      "favoritedTimes": 0,
      "id": 366651,
      "lengthSeconds": 245,
      "name": "ロウワー",
      "originalVersionId": 365108,
      "publishDate": "2021-11-19T00:00:00Z",
      "pvServices": "Youtube",
      "ratingScore": 4,
      "songType": "Cover",
      "status": "Finished",
      "version": 3
    },
    {
      "artistString": "Earthy X6 feat. various",
      "createDate": "2022-02-01T00:43:27.057",
      "defaultName": "ロウワー",
      "defaultNameLanguage": "Japanese",
      "favoritedTimes": 2,
      "id": 382363,
      "lengthSeconds": 227,
      "name": "ロウワー",
      "originalVersionId": 365108,
      "publishDate": "2021-11-20T00:00:00Z",
      "pvServices": "Youtube",
      "ratingScore": 18,
      "songType": "Cover",
      "status": "Finished",
      "version": 5
    },
    {
      "artistString": "消し炭 feat. 御霊シキ",
      "createDate": "2024-06-23T10:41:08.353",
      "defaultName": "ロウワー",
      "defaultNameLanguage": "Japanese",
      "favoritedTimes": 0,
      "id": 643123,
      "lengthSeconds": 231,
      "name": "ロウワー",
      "originalVersionId": 365108,
      "publishDate": "2021-11-20T00:00:00Z",
      "pvServices": "Youtube",
      "ratingScore": 0,
      "songType": "Cover",
      "status": "Finished",
      "version": 4
    },
    {
      "artistString": "-_Gimo_- feat. v flower, Fukase (Unknown)",
      "createDate": "2022-01-17T23:02:09.927",
      "defaultName": "ロウワー",
      "defaultNameLanguage": "Japanese",
      "favoritedTimes": 0,
      "id": 379478,
      "lengthSeconds": 231,
      "name": "ロウワー",
      "originalVersionId": 365108,
      "publishDate": "2021-11-21T00:00:00Z",
      "pvServices": "Youtube",
      "ratingScore": 0,
      "songType": "Cover",
      "status": "Finished",
      "version": 3
    },
    {
      "artistString": "Kowu feat. various",
      "createDate": "2022-02-03T18:30:31.243",
      "defaultName": "ロウワー",
      "defaultNameLanguage": "Japanese",
      "favoritedTimes": 1,
      "id": 383053,
      "lengthSeconds": 232,
      "name": "ロウワー",
      "originalVersionId": 365108,
      "publishDate": "2021-11-21T00:00:00Z",
      "pvServices": "Youtube",
      "ratingScore": 3,
      "songType": "Cover",
      "status": "Finished",
      "version": 2
    },
    {
      "artistString": "非試験 feat. 重音テト",
      "createDate": "2022-12-03T08:30:30.403",
      "defaultName": "ロウワー",
      "defaultNameLanguage": "Japanese",
      "favoritedTimes": 0,
      "id": 457490,
      "lengthSeconds": 230,
      "name": "ロウワー",
      "originalVersionId": 365108,
      "publishDate": "2021-11-21T00:00:00Z",
      "pvServices": "Youtube",
      "ratingScore": 2,
      "songType": "Cover",
      "status": "Finished",
      "version": 3
    },
    {
      "artistString": "Avalon feat. 健音テイ",
      "createDate": "2024-12-05T12:49:40.303",
      "defaultName": "ロウワー",
      "defaultNameLanguage": "Japanese",
      "favoritedTimes": 0,
      "id": 709149,
      "lengthSeconds": 231,
      "name": "ロウワー",
      "originalVersionId": 365108,
      "publishDate": "2021-11-24T00:00:00Z",
      "pvServices": "Youtube",
      "ratingScore": 0,
      "songType": "Cover",
      "status": "Finished",
      "version": 2
    },
    {
      "artistString": "Differential feat. KAITO V3 (Straight)",
      "createDate": "2022-02-16T17:41:32.987",
      "defaultName": "ロウワー",
      "defaultNameLanguage": "Japanese",
      "favoritedTimes": 0,
      "id": 385858,
      "lengthSeconds": 230,
      "name": "ロウワー",
      "originalVersionId": 365108,
      "publishDate": "2021-11-28T00:00:00Z",
      "pvServices": "NicoNicoDouga, Youtube",
      "ratingScore": 0,
      "songType": "Cover",
      "status": "Finished",
      "version": 3
    },
    {
      "artistString": "けにさぼう feat. ゲキヤク",
      "createDate": "2023-05-31T00:04:59.217",
      "defaultName": "ロウワー",
      "defaultNameLanguage": "Japanese",
      "favoritedTimes": 0,
      "id": 503142,
      "lengthSeconds": 230,
      "name": "ロウワー",
      "originalVersionId": 365108,
      "publishDate": "2021-11-29T00:00:00Z",
      "pvServices": "NicoNicoDouga",
      "ratingScore": 0,
      "songType": "Cover",
      "status": "Finished",
      "version": 2
    },
    {
      "artistString": "AO4 feat. 初音ミク V3 (Dark), WIL, 初音ミク V3 (Solid)",
      "createDate": "2022-03-05T08:35:40.617",
      "defaultName": "ロウワー",
      "defaultNameLanguage": "Japanese",
      "favoritedTimes": 0,
      "id": 389627,
      "lengthSeconds": 230,
      "name": "ロウワー",
      "originalVersionId": 365108,
      "publishDate": "2021-12-04T00:00:00Z",
      "pvServices": "Youtube",
      "ratingScore": 0,
      "songType": "Cover",
      "status": "Finished",
      "version": 2
    },
    {
      "artistString": "如月飛羽 feat. 闇音レンリ",
      "createDate": "2021-12-08T02:58:13.53",
      "defaultName": "ロウワー",
      "defaultNameLanguage": "Japanese",
      "favoritedTimes": 0,
      "id": 369957,
      "lengthSeconds": 230,
      "name": "ロウワー",
      "originalVersionId": 365108,
      "publishDate": "2021-12-08T00:00:00Z",
      "pvServices": "NicoNicoDouga",
      "ratingScore": 0,
      "songType": "Cover",
      "status": "Finished",
      "version": 2
    },
    {
      "artistString": "Rangea feat. 石川メイ",
      "createDate": "2022-07-30T15:44:21.99",
      "defaultName": "ロウワー / ライアーダンス",
      "defaultNameLanguage": "Japanese",
      "favoritedTimes": 0,
      "id": 428643,
      "lengthSeconds": 447,
      "name": "ロウワー / ライアーダンス",
      "originalVersionId": 365108,
      "publishDate": "2021-12-09T00:00:00Z",
      "pvServices": "Youtube",
      "ratingScore": 4,
      "songType": "Cover",
      "status": "Finished",
      "version": 5
    },
    {
      "artistString": "水桃 feat. 欲音ルコ♂",
      "createDate": "2024-06-20T12:04:50.66",
      "defaultName": "ロウワー",
      "defaultNameLanguage": "Japanese",
      "favoritedTimes": 0,
      "id": 642137,
      "lengthSeconds": 230,
      "name": "ロウワー",
      "originalVersionId": 365108,
      "publishDate": "2021-12-10T00:00:00Z",
      "pvServices": "Youtube",
      "ratingScore": 0,
      "songType": "Cover",
      "status": "Finished",
      "version": 1
    },
    {
      "artistString": "Platonic水を食べる feat. Saki AI, 闇音レンリ",
      "createDate": "2021-12-15T01:12:35.687",
      "defaultName": "ロウワー",
      "defaultNameLanguage": "Japanese",
      "favoritedTimes": 1,
      "id": 371073,
      "lengthSeconds": 231,
      "name": "ロウワー",
      "originalVersionId": 365108,
      "publishDate": "2021-12-14T00:00:00Z",
      "pvServices": "Youtube",
      "ratingScore": 3,
      "songType": "Cover",
      "status": "Finished",
      "version": 2
    },
    {
      "artistString": "Basil feat. Fukase (Unknown)",
      "createDate": "2024-06-08T21:51:57.41",
      "defaultName": "ロウワー",
      "defaultNameLanguage": "Japanese",
      "favoritedTimes": 0,
      "id": 638441,
      "lengthSeconds": 231,
      "name": "ロウワー",
      "originalVersionId": 365108,
      "publishDate": "2021-12-18T00:00:00Z",
      "pvServices": "Youtube",
      "ratingScore": 0,
      "songType": "Cover",
      "status": "Finished",
      "version": 2
    },
    {
      "artistString": "ロコモ feat. 赤咲湊",
      "createDate": "2023-02-16T04:24:20.963",
      "defaultName": "ロウワー",
      "defaultNameLanguage": "Japanese",
      "favoritedTimes": 1,
      "id": 475838,
      "lengthSeconds": 226,
      "name": "ロウワー",
      "originalVersionId": 365108,
      "publishDate": "2022-01-06T00:00:00Z",
      "pvServices": "NicoNicoDouga, Youtube",
      "ratingScore": 3,
      "songType": "Cover",
      "status": "Finished",
      "version": 4
    },
    {
      "artistString": "Rowle feat. KAITO V3 (Soft), 神威がくぽ",
      "createDate": "2024-05-11T18:08:39.317",
      "defaultName": "ロウワー",
      "defaultNameLanguage": "Japanese",
      "favoritedTimes": 0,
      "id": 626671,
      "lengthSeconds": 231,
      "name": "ロウワー",
      "originalVersionId": 365108,
      "publishDate": "2022-01-07T00:00:00Z",
      "pvServices": "Youtube",
      "ratingScore": 0,
      "songType": "Cover",
      "status": "Finished",
      "version": 2
    },
    {
      "artistString": "u-z feat. v4 flower",
      "createDate": "2022-06-01T04:54:26.66",
      "defaultName": "ロウワー(u-z Jazzy Gothic Remix)",
      "defaultNameLanguage": "Japanese",
      "favoritedTimes": 0,
      "id": 410836,
      "lengthSeconds": 196,
      "name": "ロウワー(u-z Jazzy Gothic Remix)",
      "originalVersionId": 365108,
      "publishDate": "2022-01-12T00:00:00Z",
      "pvServices": "NicoNicoDouga, Youtube, SoundCloud",
      "ratingScore": 2,
      "songType": "Remix",
      "status": "Finished",
      "version": 5
    },
    {
      "artistString": "Du Du Danyon feat. SOLARIA",
      "createDate": "2022-01-13T17:19:33.743",
      "defaultName": "ロウワー",
      "defaultNameLanguage": "Japanese",
      "favoritedTimes": 1,
      "id": 378637,
      "lengthSeconds": 110,
      "name": "ロウワー",
      "originalVersionId": 365108,
      "publishDate": "2022-01-13T00:00:00Z",
      "pvServices": "Youtube, SoundCloud",
      "ratingScore": 5,
      "songType": "Cover",
      "status": "Finished",
      "version": 3
    },
    {
      "artistString": "CircusP feat. SOLARIA",
      "createDate": "2022-01-14T05:03:33.637",
      "defaultName": "ロウワー",
      "defaultNameLanguage": "Japanese",
      "favoritedTimes": 3,
      "id": 378746,
      "lengthSeconds": 229,
      "name": "ロウワー",
      "originalVersionId": 365108,
      "publishDate": "2022-01-14T00:00:00Z",
      "pvServices": "Youtube, Bilibili",
      "ratingScore": 25,
      "songType": "Cover",
      "status": "Finished",
      "version": 4
    },
    {
      "artistString": "MiyukiHikawa18 feat. KAITO V3 (Unknown), 巡音ルカ V4X (Unknown)",
      "createDate": "2022-01-26T05:32:45.1",
      "defaultName": "ロウワー",
      "defaultNameLanguage": "Japanese",
      "favoritedTimes": 0,
      "id": 381137,
      "lengthSeconds": 231,
      "name": "ロウワー",
      "originalVersionId": 365108,
      "publishDate": "2022-01-15T00:00:00Z",
      "pvServices": "Youtube",
      "ratingScore": 0,
      "songType": "Cover",
      "status": "Finished",
      "version": 2
    },
    {
      "artistString": "MiyukiHikawa18 feat. MEIKO V3 (Unknown), 初音ミク V4X (Unknown)",
      "createDate": "2022-01-26T05:31:53.667",
      "defaultName": "ロウワー",
      "defaultNameLanguage": "Japanese",
      "favoritedTimes": 0,
      "id": 381136,
      "lengthSeconds": 231,
      "name": "ロウワー",
      "originalVersionId": 365108,
      "publishDate": "2022-01-22T00:00:00Z",
      "pvServices": "Youtube",
      "ratingScore": 0,
      "songType": "Cover",
      "status": "Finished",
      "version": 2
    },
    {
      "artistString": "Aurazour feat. 小春六花 AI",
      "createDate": "2024-10-29T21:22:32.917",
      "defaultName": "ロウワー",
      "defaultNameLanguage": "Japanese",
      "favoritedTimes": 0,
      "id": 691945,
      "lengthSeconds": 230,
      "name": "ロウワー",
      "originalVersionId": 365108,
      "publishDate": "2022-01-23T00:00:00Z",
      "pvServices": "Youtube",
      "ratingScore": 0,
      "songType": "Cover",
      "status": "Finished",
      "version": 3
    },
    {
      "artistString": "Scarlet桑戎 feat. 言和 V5 (沐), 言和 V5 (清)",
      "createDate": "2024-11-23T07:41:16.15",
      "defaultName": "ロウワ―",
      "defaultNameLanguage": "Japanese",
      "favoritedTimes": 0,
      "id": 704259,
      "lengthSeconds": 231,
      "name": "ロウワ―",
      "originalVersionId": 365108,
      "publishDate": "2022-01-28T00:00:00Z",
      "pvServices": "Bilibili",
      "ratingScore": 0,
      "songType": "Cover",
      "status": "Finished",
      "version": 2
    },
    {
      "artistString": "nightmare feat. SOLARIA",
      "createDate": "2022-01-29T12:05:02.11",
      "defaultName": "ロウワー",
      "defaultNameLanguage": "Japanese",
      "favoritedTimes": 2,
      "id": 382057,
      "lengthSeconds": 230,
      "name": "ロウワー",
      "originalVersionId": 365108,
      "publishDate": "2022-01-29T00:00:00Z",
      "pvServices": "Youtube",
      "ratingScore": 14,
      "songType": "Cover",
      "status": "Finished",
      "version": 9
    },
    {
      "artistString": "鈴卵 feat. GUMI",
      "createDate": "2024-11-27T07:25:38.23",
      "defaultName": "ロウワー",
      "defaultNameLanguage": "Japanese",
      "favoritedTimes": 0,
      "id": 705654,
      "lengthSeconds": 229,
      "name": "ロウワー",
      "originalVersionId": 365108,
      "publishDate": "2022-02-03T00:00:00Z",
      "pvServices": "NicoNicoDouga",
      "ratingScore": 0,
      "songType": "Cover",
      "status": "Finished",
      "version": 1
    },
    {
      "artistString": "セブヶ崎詠人 feat. Ryo",
      "createDate": "2023-06-16T04:23:23.767",
      "defaultName": "ロウワー",
      "defaultNameLanguage": "Japanese",
      "favoritedTimes": 0,
      "id": 506603,
      "lengthSeconds": 230,
      "name": "ロウワー",
      "originalVersionId": 365108,
      "publishDate": "2022-02-05T00:00:00Z",
      "pvServices": "NicoNicoDouga",
      "ratingScore": 0,
      "songType": "Cover",
      "status": "Finished",
      "version": 2
    },
    {
      "artistString": "もちもちP feat. さとうささら (CeVIO AI)",
      "createDate": "2022-02-18T22:07:49.267",
      "defaultName": "ロウワー",
      "defaultNameLanguage": "Japanese",
      "favoritedTimes": 0,
      "id": 386247,
      "lengthSeconds": 230,
      "name": "ロウワー",
      "originalVersionId": 365108,
      "publishDate": "2022-02-10T00:00:00Z",
      "pvServices": "NicoNicoDouga",
      "ratingScore": 2,
      "songType": "Cover",
      "status": "Finished",
      "version": 2
    },
    {
      "artistString": "Ma'iitsoh Kurai feat. 鏡音レン",
      "createDate": "2024-11-16T04:12:58.627",
      "defaultName": "ロウワー",
      "defaultNameLanguage": "Japanese",
      "favoritedTimes": 0,
      "id": 700407,
      "lengthSeconds": 231,
      "name": "ロウワー",
      "originalVersionId": 365108,
      "publishDate": "2022-03-04T00:00:00Z",
      "pvServices": "Youtube",
      "ratingScore": 0,
      "songType": "Cover",
      "status": "Finished",
      "version": 2
    },
    {
      "artistString": "安打荒院 feat. 諳打荒院 良無音",
      "createDate": "2022-07-30T16:48:41.2",
      "defaultName": "ロウワー",
      "defaultNameLanguage": "Japanese",
      "favoritedTimes": 1,
      "id": 428652,
      "lengthSeconds": 104,
      "name": "ロウワー",
      "originalVersionId": 365108,
      "publishDate": "2022-03-14T00:00:00Z",
      "pvServices": "Nothing",
      "ratingScore": 5,
      "songType": "Cover",
      "status": "Finished",
      "version": 2
    },
    {
      "artistString": "愛しyou-P feat. MEIKO V3 (Dark), MEIKO V3 (Power), MEIKO V3 (Whisper)",
      "createDate": "2022-03-23T10:46:45.887",
      "defaultName": "ロウワー",
      "defaultNameLanguage": "Japanese",
      "favoritedTimes": 1,
      "id": 394362,
      "lengthSeconds": 231,
      "name": "ロウワー",
      "originalVersionId": 365108,
      "publishDate": "2022-03-22T00:00:00Z",
      "pvServices": "Youtube",
      "ratingScore": 5,
      "songType": "Cover",
      "status": "Finished",
      "version": 5
    },
    {
      "artistString": "セブヶ崎詠人 feat. MAYU",
      "createDate": "2024-02-01T09:47:43.197",
      "defaultName": "ロウワー",
      "defaultNameLanguage": "Japanese",
      "favoritedTimes": 0,
      "id": 581238,
      "lengthSeconds": 231,
      "name": "ロウワー",
      "originalVersionId": 365108,
      "publishDate": "2022-03-22T00:00:00Z",
      "pvServices": "Youtube",
      "ratingScore": 0,
      "songType": "Cover",
      "status": "Finished",
      "version": 3
    },
    {
      "artistString": "funnel_cake feat. Ryo",
      "createDate": "2022-03-24T08:38:33.833",
      "defaultName": "ロウワー",
      "defaultNameLanguage": "Japanese",
      "favoritedTimes": 0,
      "id": 394511,
      "lengthSeconds": 231,
      "name": "ロウワー",
      "originalVersionId": 365108,
      "publishDate": "2022-03-23T00:00:00Z",
      "pvServices": "Youtube",
      "ratingScore": 2,
      "songType": "Cover",
      "status": "Finished",
      "version": 2
    },
    {
      "artistString": "セブヶ崎詠人 feat. 夏色花梨",
      "createDate": "2022-04-12T14:48:05.523",
      "defaultName": "ロウワー",
      "defaultNameLanguage": "Japanese",
      "favoritedTimes": 1,
      "id": 399121,
      "lengthSeconds": 230,
      "name": "ロウワー",
      "originalVersionId": 365108,
      "publishDate": "2022-04-12T00:00:00Z",
      "pvServices": "NicoNicoDouga, Youtube",
      "ratingScore": 5,
      "songType": "Cover",
      "status": "Finished",
      "version": 3
    },
    {
      "artistString": "赤猫 feat. 初音ミク, 鏡音リン",
      "createDate": "2022-04-23T22:35:57.46",
      "defaultName": "ロウワー　REMIX ver.",
      "defaultNameLanguage": "Japanese",
      "favoritedTimes": 0,
      "id": 402028,
      "lengthSeconds": 230,
      "name": "ロウワー　REMIX ver.",
      "originalVersionId": 365108,
      "publishDate": "2022-04-23T00:00:00Z",
      "pvServices": "NicoNicoDouga, Youtube",
      "ratingScore": 2,
      "songType": "Remix",
      "status": "Finished",
      "version": 2
    },
    {
      "artistString": "大槻メトロ feat. 飴唄ニユス",
      "createDate": "2022-04-24T04:08:54.837",
      "defaultName": "ロウワー",
      "defaultNameLanguage": "Japanese",
      "favoritedTimes": 0,
      "id": 402204,
      "lengthSeconds": 231,
      "name": "ロウワー",
      "originalVersionId": 365108,
      "publishDate": "2022-04-23T00:00:00Z",
      "pvServices": "NicoNicoDouga, Youtube",
      "ratingScore": 0,
      "songType": "Cover",
      "status": "Finished",
      "version": 4
    },
    {
      "artistString": "Nate · Lightbringer feat. 巡音ルカ",
      "createDate": "2022-05-23T07:10:49.313",
      "defaultName": "ロウワー",
      "defaultNameLanguage": "Japanese",
      "favoritedTimes": 0,
      "id": 408602,
      "lengthSeconds": 231,
      "name": "ロウワー",
      "originalVersionId": 365108,
      "publishDate": "2022-04-23T00:00:00Z",
      "pvServices": "Nothing",
      "ratingScore": 2,
      "songType": "Cover",
      "status": "Finished",
      "version": 4
    },
    {
      "artistString": "デスレガ feat. v4 flower",
      "createDate": "2023-02-13T22:02:01.983",
      "defaultName": "ロウワー",
      "defaultNameLanguage": "Japanese",
      "favoritedTimes": 0,
      "id": 475278,
      "lengthSeconds": 230,
      "name": "ロウワー",
      "originalVersionId": 365108,
      "publishDate": "2022-04-23T00:00:00Z",
      "pvServices": "NicoNicoDouga, Youtube",
      "ratingScore": 0,
      "songType": "MusicPV",
      "status": "Finished",
      "version": 3
    },
    {
      "artistString": "Hidome feat. 歌手音ピコ",
      "createDate": "2023-12-02T04:47:08.347",
      "defaultName": "ロウワー",
      "defaultNameLanguage": "Japanese",
      "favoritedTimes": 0,
      "id": 557754,
      "lengthSeconds": 230,
      "name": "ロウワー",
      "originalVersionId": 365108,
      "publishDate": "2022-04-29T00:00:00Z",
      "pvServices": "Youtube",
      "ratingScore": 0,
      "songType": "Cover",
      "status": "Finished",
      "version": 3
    },
    {
      "artistString": "前てんパ feat. アベルーニ, 伊織弓鶴 (冥)",
      "createDate": "2022-09-23T21:13:51.853",
      "defaultName": "ロウワー",
      "defaultNameLanguage": "Japanese",
      "favoritedTimes": 0,
      "id": 440551,
      "lengthSeconds": 230,
      "name": "ロウワー",
      "originalVersionId": 365108,
      "publishDate": "2022-05-02T00:00:00Z",
      "pvServices": "NicoNicoDouga, Youtube",
      "ratingScore": 0,
      "songType": "Cover",
      "status": "Finished",
      "version": 4
    },
    {
      "artistString": "ポチP feat. MEIKO, MIRIAM",
      "createDate": "2022-08-11T23:07:05.783",
      "defaultName": "ロウワー",
      "defaultNameLanguage": "Japanese",
      "favoritedTimes": 0,
      "id": 431522,
      "lengthSeconds": 229,
      "name": "ロウワー",
      "originalVersionId": 365108,
      "publishDate": "2022-05-03T00:00:00Z",
      "pvServices": "NicoNicoDouga",
      "ratingScore": 0,
      "songType": "Cover",
      "status": "Finished",
      "version": 2
    },
    {
      "artistString": "Tax feat. 初音ミク V4X (Unknown)",
      "createDate": "2022-11-20T21:26:21.573",
      "defaultName": "ロウワー",
      "defaultNameLanguage": "Japanese",
      "favoritedTimes": 0,
      "id": 455241,
      "lengthSeconds": 231,
      "name": "ロウワー",
      "originalVersionId": 365108,
      "publishDate": "2022-05-07T00:00:00Z",
      "pvServices": "Nothing",
      "ratingScore": 2,
      "songType": "Cover",
      "status": "Finished",
      "version": 3
    },
    {
      "artistString": "雪银 feat. 岸晓",
      "createDate": "2024-09-08T19:55:14.873",
      "defaultName": "ロウワー",
      "defaultNameLanguage": "Japanese",
      "favoritedTimes": 0,
      "id": 671816,
      "lengthSeconds": 231,
      "name": "ロウワー",
      "originalVersionId": 365108,
      "publishDate": "2022-05-13T00:00:00Z",
      "pvServices": "Youtube",
      "ratingScore": 0,
      "songType": "Cover",
      "status": "Finished",
      "version": 3
    },
    {
      "artistString": "Tax feat. MEIKO V3 (Unknown)",
      "createDate": "2022-11-20T21:25:42.613",
      "defaultName": "ロウワー",
      "defaultNameLanguage": "Japanese",
      "favoritedTimes": 0,
      "id": 455240,
      "lengthSeconds": 231,
      "name": "ロウワー",
      "originalVersionId": 365108,
      "publishDate": "2022-05-29T00:00:00Z",
      "pvServices": "Youtube",
      "ratingScore": 2,
      "songType": "Cover",
      "status": "Finished",
      "version": 2
    },
    {
      "artistString": "清水寺 feat. Number Bronze",
      "createDate": "2024-07-01T04:37:45.477",
      "defaultName": "ロウワー",
      "defaultNameLanguage": "Japanese",
      "favoritedTimes": 0,
      "id": 645231,
      "lengthSeconds": 231,
      "name": "ロウワー",
      "originalVersionId": 365108,
      "publishDate": "2022-05-31T00:00:00Z",
      "pvServices": "Youtube",
      "ratingScore": 2,
      "songType": "Cover",
      "status": "Finished",
      "version": 2
    },
    {
      "artistString": "蒼白 feat. しろさきあや, Mizka",
      "createDate": "2022-10-17T09:28:12.777",
      "defaultName": "ロウワー",
      "defaultNameLanguage": "Japanese",
      "favoritedTimes": 0,
      "id": 446601,
      "lengthSeconds": 230,
      "name": "ロウワー",
      "originalVersionId": 365108,
      "publishDate": "2022-06-10T00:00:00Z",
      "pvServices": "NicoNicoDouga, Youtube",
      "ratingScore": 2,
      "songType": "Cover",
      "status": "Finished",
      "version": 6
    },
    {
      "artistString": "くろね feat. 初音ミク",
      "createDate": "2022-06-19T23:45:19.977",
      "defaultName": "ロウワー",
      "defaultNameLanguage": "Japanese",
      "favoritedTimes": 1,
      "id": 415062,
      "lengthSeconds": 42,
      "name": "ロウワー",
      "originalVersionId": 365108,
      "publishDate": "2022-06-17T00:00:00Z",
      "pvServices": "Youtube",
      "ratingScore": 3,
      "songType": "Remix",
      "status": "Finished",
      "version": 2
    },
    {
      "artistString": "tsumugilovemail feat. KYO, YOHIOloid (Japanese)",
      "createDate": "2023-01-11T07:27:34.433",
      "defaultName": "ロウワー",
      "defaultNameLanguage": "Japanese",
      "favoritedTimes": 0,
      "id": 467068,
      "lengthSeconds": 231,
      "name": "ロウワー",
      "originalVersionId": 365108,
      "publishDate": "2022-06-19T00:00:00Z",
      "pvServices": "Youtube",
      "ratingScore": 0,
      "songType": "Cover",
      "status": "Finished",
      "version": 2
    },
    {
      "artistString": "Noodle Rain feat. MEIKO V3 (Straight), 結月ゆかり, MEIKO V3 (Power)",
      "createDate": "2024-05-27T19:12:18.877",
      "defaultName": "ロウワー",
      "defaultNameLanguage": "Japanese",
      "favoritedTimes": 0,
      "id": 633553,
      "lengthSeconds": 231,
      "name": "ロウワー",
      "originalVersionId": 365108,
      "publishDate": "2022-06-23T00:00:00Z",
      "pvServices": "Youtube",
      "ratingScore": 0,
      "songType": "Cover",
      "status": "Finished",
      "version": 2
    },
    {
      "artistString": "前てんパ feat. 水音ラル",
      "createDate": "2023-07-25T14:08:23.857",
      "defaultName": "ロウワー",
      "defaultNameLanguage": "Japanese",
      "favoritedTimes": 0,
      "id": 516111,
      "lengthSeconds": 231,
      "name": "ロウワー",
      "originalVersionId": 365108,
      "publishDate": "2022-07-10T00:00:00Z",
      "pvServices": "Youtube",
      "ratingScore": 0,
      "songType": "Cover",
      "status": "Finished",
      "version": 2
    },
    {
      "artistString": "前てんパ feat. マエテンパ",
      "createDate": "2023-07-25T14:19:02.073",
      "defaultName": "ロウワー",
      "defaultNameLanguage": "Japanese",
      "favoritedTimes": 0,
      "id": 516120,
      "lengthSeconds": 231,
      "name": "ロウワー",
      "originalVersionId": 365108,
      "publishDate": "2022-07-14T00:00:00Z",
      "pvServices": "Youtube",
      "ratingScore": 0,
      "songType": "Cover",
      "status": "Finished",
      "version": 4
    },
    {
      "artistString": "008 feat. Eleanor Forte",
      "createDate": "2023-05-19T20:02:52.673",
      "defaultName": "ロウワー",
      "defaultNameLanguage": "Japanese",
      "favoritedTimes": 0,
      "id": 500641,
      "lengthSeconds": 97,
      "name": "ロウワー",
      "originalVersionId": 365108,
      "publishDate": "2022-08-11T00:00:00Z",
      "pvServices": "Youtube",
      "ratingScore": 0,
      "songType": "Cover",
      "status": "Finished",
      "version": 4
    },
    {
      "artistString": "前てんパ feat. 水奈瀬コウ",
      "createDate": "2023-07-25T18:40:27.653",
      "defaultName": "ロウワー",
      "defaultNameLanguage": "Japanese",
      "favoritedTimes": 0,
      "id": 516176,
      "lengthSeconds": 231,
      "name": "ロウワー",
      "originalVersionId": 365108,
      "publishDate": "2022-08-13T00:00:00Z",
      "pvServices": "Youtube",
      "ratingScore": 0,
      "songType": "Cover",
      "status": "Finished",
      "version": 3
    },
    {
      "artistString": "Kanabon Steaven feat. 健音テイ",
      "createDate": "2024-05-23T12:13:51.01",
      "defaultName": "ロウワー",
      "defaultNameLanguage": "Japanese",
      "favoritedTimes": 0,
      "id": 631430,
      "lengthSeconds": 95,
      "name": "ロウワー",
      "originalVersionId": 365108,
      "publishDate": "2022-08-16T00:00:00Z",
      "pvServices": "Youtube",
      "ratingScore": 0,
      "songType": "Cover",
      "status": "Finished",
      "version": 2
    },
    {
      "artistString": "Various artists",
      "createDate": "2022-10-11T19:01:29.357",
      "defaultName": "ロウワー",
      "defaultNameLanguage": "Japanese",
      "favoritedTimes": 0,
      "id": 445110,
      "lengthSeconds": 228,
      "name": "ロウワー",
      "originalVersionId": 365108,
      "publishDate": "2022-08-18T00:00:00Z",
      "pvServices": "Youtube",
      "ratingScore": 0,
      "songType": "MusicPV",
      "status": "Draft",
      "version": 6
    },
    {
      "artistString": "夏風スカイ feat. 星界",
      "createDate": "2024-02-17T15:45:28.113",
      "defaultName": "ロウワー",
      "defaultNameLanguage": "Japanese",
      "favoritedTimes": 0,
      "id": 586889,
      "lengthSeconds": 231,
      "name": "ロウワー",
      "originalVersionId": 365108,
      "publishDate": "2022-09-01T00:00:00Z",
      "pvServices": "Youtube",
      "ratingScore": 0,
      "songType": "Cover",
      "status": "Finished",
      "version": 2
    },
    {
      "artistString": "KAT feat. 初音ミク V4X (Dark)",
      "createDate": "2023-05-05T21:38:14.577",
      "defaultName": "ロウワー",
      "defaultNameLanguage": "Japanese",
      "favoritedTimes": 1,
      "id": 497394,
      "lengthSeconds": 231,
      "name": "ロウワー",
      "originalVersionId": 365108,
      "publishDate": "2022-09-17T00:00:00Z",
      "pvServices": "Youtube",
      "ratingScore": 3,
      "songType": "Cover",
      "status": "Finished",
      "version": 2
    },
    {
      "artistString": "松葉 feat. 刹葬セツリ",
      "createDate": "2023-02-04T00:40:54.573",
      "defaultName": "ロウワー",
      "defaultNameLanguage": "Japanese",
      "favoritedTimes": 0,
      "id": 473141,
      "lengthSeconds": 231,
      "name": "ロウワー",
      "originalVersionId": 365108,
      "publishDate": "2022-10-03T00:00:00Z",
      "pvServices": "NicoNicoDouga, Youtube",
      "ratingScore": 0,
      "songType": "Cover",
      "status": "Finished",
      "version": 3
    },
    {
      "artistString": "Creuzer feat. Yuma",
      "createDate": "2022-10-07T12:18:51.25",
      "defaultName": "ロウワー",
      "defaultNameLanguage": "Japanese",
      "favoritedTimes": 0,
      "id": 443360,
      "lengthSeconds": 231,
      "name": "ロウワー",
      "originalVersionId": 365108,
      "publishDate": "2022-10-07T00:00:00Z",
      "pvServices": "NicoNicoDouga, Youtube, Bilibili",
      "ratingScore": 10,
      "songType": "Cover",
      "status": "Finished",
      "version": 5
    },
    {
      "artistString": "まおたん feat. 鏡音リン Append (Power)",
      "createDate": "2024-01-01T20:44:06.323",
      "defaultName": "ロウアー",
      "defaultNameLanguage": "Japanese",
      "favoritedTimes": 0,
      "id": 570050,
      "lengthSeconds": 229,
      "name": "ロウアー",
      "originalVersionId": 365108,
      "publishDate": "2022-10-09T00:00:00Z",
      "pvServices": "Youtube",
      "ratingScore": 2,
      "songType": "Cover",
      "status": "Finished",
      "version": 2
    },
    {
      "artistString": "Froggy feat. 夏目悠李 (NNSVS)",
      "createDate": "2022-10-10T23:15:50.947",
      "defaultName": "ロウワー",
      "defaultNameLanguage": "Japanese",
      "favoritedTimes": 1,
      "id": 444677,
      "lengthSeconds": 229,
      "name": "ロウワー",
      "originalVersionId": 365108,
      "publishDate": "2022-10-10T00:00:00Z",
      "pvServices": "NicoNicoDouga, Youtube",
      "ratingScore": 5,
      "songType": "Cover",
      "status": "Finished",
      "version": 3
    },
    {
      "artistString": "밥버거, Shihyun feat. HARUKA, SARAH",
      "createDate": "2024-02-28T16:12:54.043",
      "defaultName": "ロウワー",
      "defaultNameLanguage": "Japanese",
      "favoritedTimes": 0,
      "id": 592689,
      "lengthSeconds": 231,
      "name": "ロウワー",
      "originalVersionId": 365108,
      "publishDate": "2022-10-15T00:00:00Z",
      "pvServices": "Youtube",
      "ratingScore": 0,
      "songType": "Cover",
      "status": "Draft",
      "version": 4
    },
    {
      "artistString": "Yokaill feat. 吸牙音セシル",
      "createDate": "2023-11-02T03:33:55.85",
      "defaultName": "ロウワー",
      "defaultNameLanguage": "Japanese",
      "favoritedTimes": 0,
      "id": 542628,
      "lengthSeconds": 237,
      "name": "ロウワー",
      "originalVersionId": 365108,
      "publishDate": "2022-10-23T00:00:00Z",
      "pvServices": "Youtube",
      "ratingScore": 0,
      "songType": "Cover",
      "status": "Finished",
      "version": 3
    },
    {
      "artistString": "Nekinya-P feat. various",
      "createDate": "2024-12-27T06:15:05.707",
      "defaultName": "ロウワー",
      "defaultNameLanguage": "Japanese",
      "favoritedTimes": 0,
      "id": 720413,
      "lengthSeconds": 233,
      "name": "ロウワー",
      "originalVersionId": 365108,
      "publishDate": "2022-10-31T00:00:00Z",
      "pvServices": "Youtube",
      "ratingScore": 0,
      "songType": "Cover",
      "status": "Draft",
      "version": 2
    },
    {
      "artistString": "衣更着ミサキ feat. 四国めたん",
      "createDate": "2022-12-06T03:32:50.2",
      "defaultName": "ロウワー",
      "defaultNameLanguage": "Japanese",
      "favoritedTimes": 0,
      "id": 458059,
      "lengthSeconds": 229,
      "name": "ロウワー",
      "originalVersionId": 365108,
      "publishDate": "2022-11-04T00:00:00Z",
      "pvServices": "NicoNicoDouga",
      "ratingScore": 0,
      "songType": "Cover",
      "status": "Finished",
      "version": 1
    },
    {
      "artistString": "緑の実 feat. v flower",
      "createDate": "2023-11-17T02:39:56.73",
      "defaultName": "ロウワー",
      "defaultNameLanguage": "Japanese",
      "favoritedTimes": 0,
      "id": 552387,
      "lengthSeconds": 234,
      "name": "ロウワー",
      "originalVersionId": 365108,
      "publishDate": "2022-11-13T00:00:00Z",
      "pvServices": "Youtube",
      "ratingScore": 0,
      "songType": "MusicPV",
      "status": "Finished",
      "version": 4
    },
    {
      "artistString": "VELLIE feat. Shiro",
      "createDate": "2023-11-28T15:45:53.247",
      "defaultName": "ロウワー",
      "defaultNameLanguage": "Japanese",
      "favoritedTimes": 0,
      "id": 556623,
      "lengthSeconds": 228,
      "name": "ロウワー",
      "originalVersionId": 365108,
      "publishDate": "2022-11-15T00:00:00Z",
      "pvServices": "Youtube, SoundCloud",
      "ratingScore": 0,
      "songType": "Cover",
      "status": "Finished",
      "version": 2
    },
    {
      "artistString": "CoffeeCat12 feat. 欲音ルコ♀",
      "createDate": "2022-12-18T19:08:27.57",
      "defaultName": "ロウワー",
      "defaultNameLanguage": "Japanese",
      "favoritedTimes": 0,
      "id": 459890,
      "lengthSeconds": 231,
      "name": "ロウワー",
      "originalVersionId": 365108,
      "publishDate": "2022-11-29T00:00:00Z",
      "pvServices": "Youtube",
      "ratingScore": 2,
      "songType": "Cover",
      "status": "Finished",
      "version": 2
    },
    {
      "artistString": "ロシーさん feat. 初音ミク V4X (Dark)",
      "createDate": "2023-10-07T09:15:29.37",
      "defaultName": "ロウワー",
      "defaultNameLanguage": "Japanese",
      "favoritedTimes": 0,
      "id": 534613,
      "lengthSeconds": 231,
      "name": "ロウワー",
      "originalVersionId": 365108,
      "publishDate": "2022-12-21T00:00:00Z",
      "pvServices": "Youtube",
      "ratingScore": 0,
      "songType": "Cover",
      "status": "Finished",
      "version": 2
    },
    {
      "artistString": "ちかの, いつり feat. 花撫シア AI (ENUNU)",
      "createDate": "2022-12-25T08:00:19.993",
      "defaultName": "ロウワー",
      "defaultNameLanguage": "Japanese",
      "favoritedTimes": 1,
      "id": 461015,
      "lengthSeconds": 231,
      "name": "ロウワー",
      "originalVersionId": 365108,
      "publishDate": "2022-12-24T00:00:00Z",
      "pvServices": "NicoNicoDouga, Youtube",
      "ratingScore": 3,
      "songType": "Cover",
      "status": "Finished",
      "version": 4
    },
    {
      "artistString": "4696botan feat. 琴葉葵, 琴葉茜",
      "createDate": "2023-08-20T23:20:47.087",
      "defaultName": "ロウワー",
      "defaultNameLanguage": "Japanese",
      "favoritedTimes": 0,
      "id": 523488,
      "lengthSeconds": 230,
      "name": "ロウワー",
      "originalVersionId": 365108,
      "publishDate": "2023-01-11T00:00:00Z",
      "pvServices": "NicoNicoDouga, Youtube",
      "ratingScore": 0,
      "songType": "Cover",
      "status": "Finished",
      "version": 3
    },
    {
      "artistString": "ゆめうつうつ feat. 双葉湊音",
      "createDate": "2023-01-29T00:42:37.62",
      "defaultName": "ロウワー",
      "defaultNameLanguage": "Japanese",
      "favoritedTimes": 0,
      "id": 471491,
      "lengthSeconds": 230,
      "name": "ロウワー",
      "originalVersionId": 365108,
      "publishDate": "2023-01-23T00:00:00Z",
      "pvServices": "NicoNicoDouga",
      "ratingScore": 0,
      "songType": "Cover",
      "status": "Finished",
      "version": 5
    },
    {
      "artistString": "OrangeElectric feat. KAITO V3 (Straight), MEIKO V3 (Power)",
      "createDate": "2024-01-11T21:08:43.04",
      "defaultName": "ロウワー",
      "defaultNameLanguage": "Japanese",
      "favoritedTimes": 1,
      "id": 573531,
      "lengthSeconds": 234,
      "name": "ロウワー",
      "originalVersionId": 365108,
      "publishDate": "2023-02-14T00:00:00Z",
      "pvServices": "Youtube",
      "ratingScore": 3,
      "songType": "Cover",
      "status": "Finished",
      "version": 2
    },
    {
      "artistString": "ネてル feat. 花隈千冬",
      "createDate": "2023-10-28T21:54:52.103",
      "defaultName": "ロウワー",
      "defaultNameLanguage": "Japanese",
      "favoritedTimes": 0,
      "id": 541016,
      "lengthSeconds": 229,
      "name": "ロウワー",
      "originalVersionId": 365108,
      "publishDate": "2023-03-21T00:00:00Z",
      "pvServices": "NicoNicoDouga, Youtube",
      "ratingScore": 0,
      "songType": "Remix",
      "status": "Finished",
      "version": 4
    },
    {
      "artistString": "Alfyn Li-Wolfe feat. 花隈千冬",
      "createDate": "2024-04-28T19:38:20.577",
      "defaultName": "ロウワー",
      "defaultNameLanguage": "Japanese",
      "favoritedTimes": 0,
      "id": 618272,
      "lengthSeconds": 231,
      "name": "ロウワー",
      "originalVersionId": 365108,
      "publishDate": "2023-03-30T00:00:00Z",
      "pvServices": "Youtube",
      "ratingScore": 0,
      "songType": "Cover",
      "status": "Finished",
      "version": 3
    },
    {
      "artistString": "ELGD feat. Ci flower",
      "createDate": "2023-06-12T01:55:53.657",
      "defaultName": "ロウワー",
      "defaultNameLanguage": "Japanese",
      "favoritedTimes": 0,
      "id": 505890,
      "lengthSeconds": 230,
      "name": "ロウワー",
      "originalVersionId": 365108,
      "publishDate": "2023-04-11T00:00:00Z",
      "pvServices": "Youtube, SoundCloud",
      "ratingScore": 0,
      "songType": "Cover",
      "status": "Finished",
      "version": 3
    },
    {
      "artistString": "が と feat. カフィン",
      "createDate": "2023-11-12T14:42:18.88",
      "defaultName": "ロウワー",
      "defaultNameLanguage": "Japanese",
      "favoritedTimes": 0,
      "id": 551043,
      "lengthSeconds": 233,
      "name": "ロウワー",
      "originalVersionId": 365108,
      "publishDate": "2023-04-22T00:00:00Z",
      "pvServices": "NicoNicoDouga",
      "ratingScore": 0,
      "songType": "Cover",
      "status": "Finished",
      "version": 3
    },
    {
      "artistString": "bug feat. ASTERIAN",
      "createDate": "2023-12-19T17:31:04.813",
      "defaultName": "ロウワー",
      "defaultNameLanguage": "Japanese",
      "favoritedTimes": 0,
      "id": 565230,
      "lengthSeconds": 230,
      "name": "ロウワー",
      "originalVersionId": 365108,
      "publishDate": "2023-04-23T00:00:00Z",
      "pvServices": "Youtube",
      "ratingScore": 0,
      "songType": "Cover",
      "status": "Finished",
      "version": 3
    },
    {
      "artistString": "Lucifer feat. 重音テトSV",
      "createDate": "2023-04-27T05:59:29.613",
      "defaultName": "ロウワー",
      "defaultNameLanguage": "Japanese",
      "favoritedTimes": 1,
      "id": 495311,
      "lengthSeconds": 231,
      "name": "ロウワー",
      "originalVersionId": 365108,
      "publishDate": "2023-04-27T00:00:00Z",
      "pvServices": "Youtube",
      "ratingScore": 7,
      "songType": "Cover",
      "status": "Finished",
      "version": 2
    },
    {
      "artistString": "セブヶ崎詠人 feat. 重音テトSV",
      "createDate": "2023-05-01T22:49:34.253",
      "defaultName": "ロウワー",
      "defaultNameLanguage": "Japanese",
      "favoritedTimes": 1,
      "id": 496289,
      "lengthSeconds": 230,
      "name": "ロウワー",
      "originalVersionId": 365108,
      "publishDate": "2023-04-27T00:00:00Z",
      "pvServices": "NicoNicoDouga, Youtube",
      "ratingScore": 3,
      "songType": "Cover",
      "status": "Finished",
      "version": 3
    },
    {
      "artistString": "Agate feat. 鏡音レン V4X (Unknown)",
      "createDate": "2024-08-06T16:07:46.553",
      "defaultName": "ロウワー",
      "defaultNameLanguage": "Japanese",
      "favoritedTimes": 0,
      "id": 657526,
      "lengthSeconds": 227,
      "name": "ロウワー",
      "originalVersionId": 365108,
      "publishDate": "2023-05-20T00:00:00Z",
      "pvServices": "Youtube",
      "ratingScore": 0,
      "songType": "MusicPV",
      "status": "Finished",
      "version": 3
    },
    {
      "artistString": "Lucifer feat. 神威がくぽ",
      "createDate": "2023-07-25T09:17:30.68",
      "defaultName": "ロウワー",
      "defaultNameLanguage": "Japanese",
      "favoritedTimes": 0,
      "id": 516043,
      "lengthSeconds": 231,
      "name": "ロウワー",
      "originalVersionId": 365108,
      "publishDate": "2023-07-22T00:00:00Z",
      "pvServices": "Youtube",
      "ratingScore": 0,
      "songType": "Cover",
      "status": "Finished",
      "version": 2
    },
    {
      "artistString": "lionine feat. v flower, 初音ミク",
      "createDate": "2023-07-26T22:13:41.233",
      "defaultName": "ロウワー",
      "defaultNameLanguage": "Japanese",
      "favoritedTimes": 0,
      "id": 516367,
      "lengthSeconds": 230,
      "name": "ロウワー",
      "originalVersionId": 365108,
      "publishDate": "2023-07-26T00:00:00Z",
      "pvServices": "Youtube",
      "ratingScore": 0,
      "songType": "Cover",
      "status": "Finished",
      "version": 2
    },
    {
      "artistString": "Trashghoul feat. 夏色花梨",
      "createDate": "2023-10-07T10:30:55.693",
      "defaultName": "ロウワー",
      "defaultNameLanguage": "Japanese",
      "favoritedTimes": 0,
      "id": 534688,
      "lengthSeconds": 228,
      "name": "ロウワー",
      "originalVersionId": 365108,
      "publishDate": "2023-07-29T00:00:00Z",
      "pvServices": "Youtube",
      "ratingScore": 0,
      "songType": "Cover",
      "status": "Finished",
      "version": 3
    },
    {
      "artistString": "あどれなりん feat. KAITO V3 (Unknown)",
      "createDate": "2024-01-30T15:18:28.91",
      "defaultName": "ロウワー",
      "defaultNameLanguage": "Japanese",
      "favoritedTimes": 0,
      "id": 580627,
      "lengthSeconds": 228,
      "name": "ロウワー",
      "originalVersionId": 365108,
      "publishDate": "2023-08-07T00:00:00Z",
      "pvServices": "NicoNicoDouga",
      "ratingScore": 0,
      "songType": "Cover",
      "status": "Finished",
      "version": 2
    },
    {
      "artistString": "下僕@縁屋きなこ feat. ずんだもん",
      "createDate": "2024-02-11T06:00:59.587",
      "defaultName": "ロウワー",
      "defaultNameLanguage": "Japanese",
      "favoritedTimes": 0,
      "id": 584990,
      "lengthSeconds": 230,
      "name": "ロウワー",
      "originalVersionId": 365108,
      "publishDate": "2023-08-08T00:00:00Z",
      "pvServices": "NicoNicoDouga, Youtube",
      "ratingScore": 0,
      "songType": "Cover",
      "status": "Finished",
      "version": 2
    },
    {
      "artistString": "MudaiP, Polar, Cosmoto feat. 知声",
      "createDate": "2024-11-22T20:04:34.563",
      "defaultName": "ロウワー",
      "defaultNameLanguage": "Japanese",
      "favoritedTimes": 0,
      "id": 704146,
      "lengthSeconds": 233,
      "name": "ロウワー",
      "originalVersionId": 365108,
      "publishDate": "2023-08-10T00:00:00Z",
      "pvServices": "Youtube",
      "ratingScore": 0,
      "songType": "Cover",
      "status": "Finished",
      "version": 4
    },
    {
      "artistString": "aro8 feat. 鏡音リン V4X (Unknown)",
      "createDate": "2023-09-03T14:23:59.673",
      "defaultName": "ロウワー",
      "defaultNameLanguage": "Japanese",
      "favoritedTimes": 0,
      "id": 526349,
      "lengthSeconds": 231,
      "name": "ロウワー",
      "originalVersionId": 365108,
      "publishDate": "2023-08-13T00:00:00Z",
      "pvServices": "Youtube",
      "ratingScore": 0,
      "songType": "Cover",
      "status": "Finished",
      "version": 3
    },
    {
      "artistString": "blackhomotoadshoe feat. 夜語トバリ",
      "createDate": "2023-09-03T00:34:22.353",
      "defaultName": "ロウワー",
      "defaultNameLanguage": "Japanese",
      "favoritedTimes": 0,
      "id": 526219,
      "lengthSeconds": 230,
      "name": "ロウワー",
      "originalVersionId": 365108,
      "publishDate": "2023-09-02T00:00:00Z",
      "pvServices": "Youtube",
      "ratingScore": 0,
      "songType": "Cover",
      "status": "Finished",
      "version": 2
    },
    {
      "artistString": "Drayo Drax feat. 竜音ドラヨ",
      "createDate": "2023-12-10T22:08:49.693",
      "defaultName": "ロウワー",
      "defaultNameLanguage": "Japanese",
      "favoritedTimes": 0,
      "id": 561404,
      "lengthSeconds": 231,
      "name": "ロウワー",
      "originalVersionId": 365108,
      "publishDate": "2023-09-10T00:00:00Z",
      "pvServices": "NicoNicoDouga, Youtube",
      "ratingScore": 0,
      "songType": "Cover",
      "status": "Finished",
      "version": 3
    },
    {
      "artistString": "もかな feat. 春日部つむぎ",
      "createDate": "2023-11-03T05:15:27.047",
      "defaultName": "ロウワー",
      "defaultNameLanguage": "Japanese",
      "favoritedTimes": 0,
      "id": 543393,
      "lengthSeconds": 99,
      "name": "ロウワー",
      "originalVersionId": 365108,
      "publishDate": "2023-09-11T00:00:00Z",
      "pvServices": "Youtube",
      "ratingScore": 0,
      "songType": "Cover",
      "status": "Finished",
      "version": 3
    },
    {
      "artistString": "Carosy一玫 feat. 足立レイ",
      "createDate": "2024-08-11T23:37:40.99",
      "defaultName": "Lower",
      "defaultNameLanguage": "English",
      "favoritedTimes": 0,
      "id": 660436,
      "lengthSeconds": 230,
      "name": "Lower",
      "originalVersionId": 365108,
      "publishDate": "2023-11-12T00:00:00Z",
      "pvServices": "Bilibili",
      "ratingScore": 0,
      "songType": "Cover",
      "status": "Finished",
      "version": 2
    },
    {
      "artistString": "Somna-P feat. 星尘Infinity",
      "createDate": "2024-12-06T01:15:01.893",
      "defaultName": "ロウワー",
      "defaultNameLanguage": "Japanese",
      "favoritedTimes": 0,
      "id": 709453,
      "lengthSeconds": 231,
      "name": "ロウワー",
      "originalVersionId": 365108,
      "publishDate": "2023-11-12T00:00:00Z",
      "pvServices": "Youtube",
      "ratingScore": 0,
      "songType": "Cover",
      "status": "Finished",
      "version": 3
    },
    {
      "artistString": "ルア feat. 欲音ルコ♀",
      "createDate": "2023-11-18T01:19:50.22",
      "defaultName": "ロウワー",
      "defaultNameLanguage": "Japanese",
      "favoritedTimes": 0,
      "id": 552630,
      "lengthSeconds": 230,
      "name": "ロウワー",
      "originalVersionId": 365108,
      "publishDate": "2023-11-17T00:00:00Z",
      "pvServices": "NicoNicoDouga, Youtube",
      "ratingScore": 0,
      "songType": "Cover",
      "status": "Finished",
      "version": 3
    },
    {
      "artistString": "灯生 feat. 重音テト",
      "createDate": "2023-12-03T22:23:49",
      "defaultName": "ロウワー",
      "defaultNameLanguage": "Japanese",
      "favoritedTimes": 0,
      "id": 558424,
      "lengthSeconds": 229,
      "name": "ロウワー",
      "originalVersionId": 365108,
      "publishDate": "2023-12-02T00:00:00Z",
      "pvServices": "NicoNicoDouga",
      "ratingScore": 0,
      "songType": "Cover",
      "status": "Finished",
      "version": 6
    },
    {
      "artistString": "Callakii feat. Synthesizer V AI Megpoid",
      "createDate": "2023-12-20T17:03:21.293",
      "defaultName": "ロウワー",
      "defaultNameLanguage": "Japanese",
      "favoritedTimes": 0,
      "id": 565702,
      "lengthSeconds": 231,
      "name": "ロウワー",
      "originalVersionId": 365108,
      "publishDate": "2023-12-20T00:00:00Z",
      "pvServices": "Youtube",
      "ratingScore": 2,
      "songType": "Cover",
      "status": "Finished",
      "version": 3
    },
    {
      "artistString": "TODO feat. Synthesizer V AI Megpoid",
      "createDate": "2024-01-09T00:35:20.54",
      "defaultName": "ロウワー",
      "defaultNameLanguage": "Japanese",
      "favoritedTimes": 0,
      "id": 572671,
      "lengthSeconds": 227,
      "name": "ロウワー",
      "originalVersionId": 365108,
      "publishDate": "2023-12-26T00:00:00Z",
      "pvServices": "Youtube",
      "ratingScore": 0,
      "songType": "Cover",
      "status": "Finished",
      "version": 3
    },
    {
      "artistString": "리미 feat. 重音テトSV",
      "createDate": "2025-01-02T11:28:11.9",
      "defaultName": "ロウワー",
      "defaultNameLanguage": "Japanese",
      "favoritedTimes": 0,
      "id": 723916,
      "lengthSeconds": 231,
      "name": "ロウワー",
      "originalVersionId": 365108,
      "publishDate": "2023-12-29T00:00:00Z",
      "pvServices": "Youtube",
      "ratingScore": 2,
      "songType": "Cover",
      "status": "Finished",
      "version": 2
    },
    {
      "artistString": "辺々あいら feat. 辺音ライア",
      "createDate": "2024-01-07T10:09:57.823",
      "defaultName": "ロウワー",
      "defaultNameLanguage": "Japanese",
      "favoritedTimes": 0,
      "id": 572061,
      "lengthSeconds": 240,
      "name": "ロウワー",
      "originalVersionId": 365108,
      "publishDate": "2023-12-30T00:00:00Z",
      "pvServices": "NicoNicoDouga",
      "ratingScore": 0,
      "songType": "Cover",
      "status": "Finished",
      "version": 5
    },
    {
      "artistString": "なななのそのか feat. ISISちゃん",
      "createDate": "2024-12-10T23:04:21.007",
      "defaultName": "ロウワー",
      "defaultNameLanguage": "Japanese",
      "favoritedTimes": 0,
      "id": 711891,
      "lengthSeconds": 230,
      "name": "ロウワー",
      "originalVersionId": 365108,
      "publishDate": "2024-02-07T00:00:00Z",
      "pvServices": "NicoNicoDouga",
      "ratingScore": 0,
      "songType": "Cover",
      "status": "Finished",
      "version": 2
    },
    {
      "artistString": "Various artists",
      "createDate": "2024-10-08T04:16:03.547",
      "defaultName": "ロウワー",
      "defaultNameLanguage": "Japanese",
      "favoritedTimes": 1,
      "id": 683961,
      "lengthSeconds": 246,
      "name": "ロウワー",
      "originalVersionId": 365108,
      "publishDate": "2024-02-23T00:00:00Z",
      "pvServices": "NicoNicoDouga",
      "ratingScore": 7,
      "songType": "Remix",
      "status": "Finished",
      "version": 5
    },
    {
      "artistString": "MAMU_매뮤 feat. 可不",
      "createDate": "2024-07-19T01:32:40.433",
      "defaultName": "ロウワー",
      "defaultNameLanguage": "Japanese",
      "favoritedTimes": 0,
      "id": 650534,
      "lengthSeconds": 268,
      "name": "ロウワー",
      "originalVersionId": 365108,
      "publishDate": "2024-03-02T00:00:00Z",
      "pvServices": "Youtube",
      "ratingScore": 0,
      "songType": "Remix",
      "status": "Finished",
      "version": 3
    },
    {
      "artistString": "psychedex feat. 重音テトSV",
      "createDate": "2024-07-22T02:23:53.237",
      "defaultName": "ロウワー",
      "defaultNameLanguage": "Japanese",
      "favoritedTimes": 0,
      "id": 651892,
      "lengthSeconds": 233,
      "name": "ロウワー",
      "originalVersionId": 365108,
      "publishDate": "2024-03-11T00:00:00Z",
      "pvServices": "Youtube",
      "ratingScore": 0,
      "songType": "Cover",
      "status": "Finished",
      "version": 3
    },
    {
      "artistString": "K-Kun, pou feat. KAITO, 巡音ルカ",
      "createDate": "2024-06-28T20:14:25.967",
      "defaultName": "ロウワー",
      "defaultNameLanguage": "Japanese",
      "favoritedTimes": 0,
      "id": 644470,
      "lengthSeconds": 231,
      "name": "ロウワー",
      "originalVersionId": 365108,
      "publishDate": "2024-03-26T00:00:00Z",
      "pvServices": "Youtube",
      "ratingScore": 0,
      "songType": "Cover",
      "status": "Finished",
      "version": 2
    },
    {
      "artistString": "ホリデイ feat. prtv_1, prtv_3",
      "createDate": "2024-05-03T20:37:07.167",
      "defaultName": "ロウワー",
      "defaultNameLanguage": "Japanese",
      "favoritedTimes": 0,
      "id": 620538,
      "lengthSeconds": 232,
      "name": "ロウワー",
      "originalVersionId": 365108,
      "publishDate": "2024-05-02T00:00:00Z",
      "pvServices": "NicoNicoDouga, Youtube",
      "ratingScore": 2,
      "songType": "Cover",
      "status": "Finished",
      "version": 3
    },
    {
      "artistString": "Starbow feat. 鳴花ヒメ, 鳴花ミコト",
      "createDate": "2024-05-08T13:13:04.403",
      "defaultName": "ロウワー",
      "defaultNameLanguage": "Japanese",
      "favoritedTimes": 0,
      "id": 622955,
      "lengthSeconds": 231,
      "name": "ロウワー",
      "originalVersionId": 365108,
      "publishDate": "2024-05-03T00:00:00Z",
      "pvServices": "Youtube",
      "ratingScore": 0,
      "songType": "Cover",
      "status": "Finished",
      "version": 3
    },
    {
      "artistString": "fearofevrything  feat. 小春六花 AI",
      "createDate": "2024-11-08T09:59:14.25",
      "defaultName": "ロウワー",
      "defaultNameLanguage": "Japanese",
      "favoritedTimes": 0,
      "id": 696107,
      "lengthSeconds": 227,
      "name": "ロウワー",
      "originalVersionId": 365108,
      "publishDate": "2024-05-14T00:00:00Z",
      "pvServices": "Youtube",
      "ratingScore": 0,
      "songType": "Cover",
      "status": "Finished",
      "version": 2
    },
    {
      "artistString": "rice feat. Hayden",
      "createDate": "2024-06-29T18:44:44.06",
      "defaultName": "ロウワー",
      "defaultNameLanguage": "Japanese",
      "favoritedTimes": 2,
      "id": 644638,
      "lengthSeconds": 229,
      "name": "ロウワー",
      "originalVersionId": 365108,
      "publishDate": "2024-06-29T00:00:00Z",
      "pvServices": "Youtube",
      "ratingScore": 10,
      "songType": "Cover",
      "status": "Finished",
      "version": 2
    },
    {
      "artistString": "空宮 ゆき feat. 成瀬ミオ",
      "createDate": "2024-12-01T00:23:05.18",
      "defaultName": "ロウワー",
      "defaultNameLanguage": "Japanese",
      "favoritedTimes": 0,
      "id": 707217,
      "lengthSeconds": 228,
      "name": "ロウワー",
      "originalVersionId": 365108,
      "publishDate": "2024-06-30T00:00:00Z",
      "pvServices": "NicoNicoDouga, Youtube",
      "ratingScore": 0,
      "songType": "Cover",
      "status": "Finished",
      "version": 3
    },
    {
      "artistString": "夏鈴 feat. various",
      "createDate": "2024-10-27T16:39:17.99",
      "defaultName": "ロウワー",
      "defaultNameLanguage": "Japanese",
      "favoritedTimes": 0,
      "id": 691323,
      "lengthSeconds": 231,
      "name": "ロウワー",
      "originalVersionId": 365108,
      "publishDate": "2024-07-07T00:00:00Z",
      "pvServices": "Youtube",
      "ratingScore": 0,
      "songType": "Cover",
      "status": "Finished",
      "version": 2
    },
    {
      "artistString": "黒ル子P feat. 欲音ルコ♀",
      "createDate": "2024-11-19T09:53:26.02",
      "defaultName": "ロウワー",
      "defaultNameLanguage": "Japanese",
      "favoritedTimes": 0,
      "id": 702224,
      "lengthSeconds": 231,
      "name": "ロウワー",
      "originalVersionId": 365108,
      "publishDate": "2024-08-14T00:00:00Z",
      "pvServices": "Youtube",
      "ratingScore": 0,
      "songType": "Cover",
      "status": "Finished",
      "version": 2
    },
    {
      "artistString": "这里是宅猫 feat. カロガド",
      "createDate": "2024-09-17T17:55:53.78",
      "defaultName": "ロウワー",
      "defaultNameLanguage": "Japanese",
      "favoritedTimes": 0,
      "id": 675571,
      "lengthSeconds": 231,
      "name": "ロウワー",
      "originalVersionId": 365108,
      "publishDate": "2024-09-07T00:00:00Z",
      "pvServices": "Bilibili",
      "ratingScore": 0,
      "songType": "Cover",
      "status": "Finished",
      "version": 2
    },
    {
      "artistString": "ksm feat. 秋山大智 AI",
      "createDate": "2024-09-24T07:02:14.99",
      "defaultName": "ロウワー",
      "defaultNameLanguage": "Japanese",
      "favoritedTimes": 1,
      "id": 678439,
      "lengthSeconds": 231,
      "name": "ロウワー",
      "originalVersionId": 365108,
      "publishDate": "2024-09-22T00:00:00Z",
      "pvServices": "Youtube",
      "ratingScore": 3,
      "songType": "Cover",
      "status": "Finished",
      "version": 2
    },
    {
      "artistString": "タカオカミズキ, Mick feat. 重音テトSV",
      "createDate": "2024-10-04T17:18:40.52",
      "defaultName": "ロウワー",
      "defaultNameLanguage": "Japanese",
      "favoritedTimes": 0,
      "id": 682452,
      "lengthSeconds": 231,
      "name": "ロウワー",
      "originalVersionId": 365108,
      "publishDate": "2024-10-04T00:00:00Z",
      "pvServices": "NicoNicoDouga, Youtube",
      "ratingScore": 4,
      "songType": "Cover",
      "status": "Finished",
      "version": 5
    },
    {
      "artistString": "Colorful Palette feat. MEIKO SP (Original)",
      "createDate": "2024-10-12T14:43:12.497",
      "defaultName": "ロウワー",
      "defaultNameLanguage": "Japanese",
      "favoritedTimes": 1,
      "id": 685597,
      "lengthSeconds": 108,
      "name": "ロウワー",
      "originalVersionId": 365108,
      "publishDate": "2024-10-12T00:00:00Z",
      "pvServices": "Youtube, Bilibili",
      "ratingScore": 5,
      "songType": "Cover",
      "status": "Finished",
      "version": 5
    },
    {
      "artistString": "protoactinium99 feat. 白止",
      "createDate": "2024-10-20T18:04:50.083",
      "defaultName": "ロウワー",
      "defaultNameLanguage": "Japanese",
      "favoritedTimes": 0,
      "id": 688549,
      "lengthSeconds": 231,
      "name": "ロウワー",
      "originalVersionId": 365108,
      "publishDate": "2024-10-17T00:00:00Z",
      "pvServices": "Youtube",
      "ratingScore": 0,
      "songType": "Cover",
      "status": "Finished",
      "version": 3
    },
    {
      "artistString": "Slumpy feat. ナノ-S",
      "createDate": "2024-10-31T20:07:35.4",
      "defaultName": "ロウワー",
      "defaultNameLanguage": "Japanese",
      "favoritedTimes": 0,
      "id": 692670,
      "lengthSeconds": 229,
      "name": "ロウワー",
      "originalVersionId": 365108,
      "publishDate": "2024-10-21T00:00:00Z",
      "pvServices": "Youtube",
      "ratingScore": 0,
      "songType": "Cover",
      "status": "Finished",
      "version": 2
    },
    {
      "artistString": "NoodleP feat. MEIKO SP (Original), KAITO SP (Original)",
      "createDate": "2024-11-02T14:53:58.71",
      "defaultName": "ロウワー",
      "defaultNameLanguage": "Japanese",
      "favoritedTimes": 0,
      "id": 693398,
      "lengthSeconds": 231,
      "name": "ロウワー",
      "originalVersionId": 365108,
      "publishDate": "2024-10-21T00:00:00Z",
      "pvServices": "Youtube",
      "ratingScore": 0,
      "songType": "Cover",
      "status": "Draft",
      "version": 2
    },
    {
      "artistString": "XioMeebo feat. 琴葉茜・葵, ANRI Arcane",
      "createDate": "2024-10-30T01:08:19.007",
      "defaultName": "ロウワー",
      "defaultNameLanguage": "Japanese",
      "favoritedTimes": 0,
      "id": 691978,
      "lengthSeconds": 232,
      "name": "ロウワー",
      "originalVersionId": 365108,
      "publishDate": "2024-10-30T00:00:00Z",
      "pvServices": "Youtube",
      "ratingScore": 0,
      "songType": "Cover",
      "status": "Finished",
      "version": 3
    },
    {
      "artistString": "알릭스 feat. 鏡音リン V4X (Power), 重音テトSV",
      "createDate": "2024-11-10T17:25:56.813",
      "defaultName": "ロウワー",
      "defaultNameLanguage": "Japanese",
      "favoritedTimes": 0,
      "id": 697085,
      "lengthSeconds": 235,
      "name": "ロウワー",
      "originalVersionId": 365108,
      "publishDate": "2024-11-10T00:00:00Z",
      "pvServices": "Youtube",
      "ratingScore": 0,
      "songType": "Cover",
      "status": "Finished",
      "version": 3
    },
    {
      "artistString": "Earthwyrm-P feat. 鏡音レン",
      "createDate": "2024-12-03T21:12:53.857",
      "defaultName": "ロウワー",
      "defaultNameLanguage": "Japanese",
      "favoritedTimes": 0,
      "id": 708554,
      "lengthSeconds": 231,
      "name": "ロウワー",
      "originalVersionId": 365108,
      "publishDate": "2024-12-03T00:00:00Z",
      "pvServices": "Youtube",
      "ratingScore": 0,
      "songType": "Cover",
      "status": "Finished",
      "version": 2
    },
    {
      "artistString": "KURO feat. KAITO",
      "createDate": "2024-12-24T10:55:31.203",
      "defaultName": "ロウワー",
      "defaultNameLanguage": "Japanese",
      "favoritedTimes": 0,
      "id": 718762,
      "lengthSeconds": 230,
      "name": "ロウワー",
      "originalVersionId": 365108,
      "publishDate": "2024-12-08T00:00:00Z",
      "pvServices": "NicoNicoDouga, Youtube",
      "ratingScore": 0,
      "songType": "Cover",
      "status": "Finished",
      "version": 2
    },
    {
      "artistString": "Aurazour feat. Stormy Okioto",
      "createDate": "2024-12-22T20:14:29.78",
      "defaultName": "ロウワー",
      "defaultNameLanguage": "Japanese",
      "favoritedTimes": 0,
      "id": 717818,
      "lengthSeconds": 230,
      "name": "ロウワー",
      "originalVersionId": 365108,
      "publishDate": "2024-12-22T00:00:00Z",
      "pvServices": "Youtube",
      "ratingScore": 0,
      "songType": "Cover",
      "status": "Finished",
      "version": 4
    },
    {
      "artistString": "twstruggie feat. ゲンブ",
      "createDate": "2024-12-24T22:48:50.777",
      "defaultName": "ロウワー",
      "defaultNameLanguage": "Japanese",
      "favoritedTimes": 0,
      "id": 719013,
      "lengthSeconds": 232,
      "name": "ロウワー",
      "originalVersionId": 365108,
      "publishDate": "2024-12-24T00:00:00Z",
      "pvServices": "Youtube, SoundCloud",
      "ratingScore": 0,
      "songType": "Cover",
      "status": "Finished",
      "version": 4
    },
    {
      "artistString": "オサキハン feat. POPY, ROSE",
      "createDate": "2025-01-05T00:12:39.627",
      "defaultName": "ロウワー",
      "defaultNameLanguage": "Japanese",
      "favoritedTimes": 0,
      "id": 725911,
      "lengthSeconds": 227,
      "name": "ロウワー",
      "originalVersionId": 365108,
      "publishDate": "2025-01-02T00:00:00Z",
      "pvServices": "Youtube",
      "ratingScore": 0,
      "songType": "Cover",
      "status": "Finished",
      "version": 2
    }
  ],
  "artists": [
    {
      "artist": {
        "additionalNames": "Speak and Spell",
        "artistType": "OtherVoiceSynthesizer",
        "deleted": false,
        "id": 128730,
        "name": "Speak & Spell",
        "pictureMime": "image/jpeg",
        "status": "Draft",
        "version": 4
      },
      "categories": "Vocalist",
      "effectiveRoles": "Default",
      "id": 1601796,
      "isCustomName": false,
      "isSupport": true,
      "name": "Speak & Spell",
      "roles": "Default"
    },
    {
      "artist": {
        "additionalNames": "v4 フラワ, VOCALOID4 Library v4 flower, ブイフォウフラワ",
        "artistType": "Vocaloid",
        "deleted": false,
        "id": 34480,
        "name": "v4 flower",
        "pictureMime": "image/png",
        "releaseDate": "2015-07-16T00:00:00Z",
        "status": "Locked",
        "version": 25
      },
      "categories": "Vocalist",
      "effectiveRoles": "Default",
      "id": 1103157,
      "isCustomName": false,
      "isSupport": false,
      "name": "v4 flower",
      "roles": "Default"
    },
    {
      "artist": {
        "additionalNames": "Ichita",
        "artistType": "Producer",
        "deleted": false,
        "id": 58977,
        "name": "いちた",
        "pictureMime": "image/jpeg",
        "status": "Finished",
        "version": 7
      },
      "categories": "Other",
      "effectiveRoles": "Instrumentalist",
      "id": 994549,
      "isCustomName": false,
      "isSupport": false,
      "name": "いちた",
      "roles": "Instrumentalist"
    },
    {
      "artist": {
        "additionalNames": "nulut, Lanndo, Nuyuri, go乱心P, ぬるり, Crona",
        "artistType": "Producer",
        "deleted": false,
        "id": 5666,
        "name": "ぬゆり",
        "pictureMime": "image/jpeg",
        "status": "Approved",
        "version": 31
      },
      "categories": "Producer",
      "effectiveRoles": "Default",
      "id": 994169,
      "isCustomName": false,
      "isSupport": false,
      "name": "ぬゆり",
      "roles": "Default"
    },
    {
      "artist": {
        "additionalNames": "Mizuki, miz_k6, mzk_i6",
        "artistType": "Animator",
        "deleted": false,
        "id": 3628,
        "name": "みず希",
        "pictureMime": "image/jpeg",
        "status": "Finished",
        "version": 8
      },
      "categories": "Animator",
      "effectiveRoles": "Animator",
      "id": 994548,
      "isCustomName": false,
      "isSupport": false,
      "name": "みず希",
      "roles": "Animator"
    },
    {
      "artist": {
        "additionalNames": "Harushi Mube",
        "artistType": "Illustrator",
        "deleted": false,
        "id": 96458,
        "name": "春私宜",
        "pictureMime": "image/png",
        "status": "Finished",
        "version": 5
      },
      "categories": "Illustrator",
      "effectiveRoles": "Illustrator",
      "id": 997333,
      "isCustomName": false,
      "isSupport": false,
      "name": "春私宜",
      "roles": "Default"
    },
    {
      "artist": {
        "additionalNames": "Nakamura Ryouma, Ryoma Nakamura, 中村リョーマ",
        "artistType": "OtherIndividual",
        "deleted": false,
        "id": 57489,
        "name": "中村涼真",
        "pictureMime": "image/jpeg",
        "status": "Finished",
        "version": 8
      },
      "categories": "Other",
      "effectiveRoles": "Mixer",
      "id": 994550,
      "isCustomName": false,
      "isSupport": false,
      "name": "中村涼真",
      "roles": "Mixer"
    }
  ],
  "artistString": "ぬゆり feat. v4 flower",
  "canEditPersonalDescription": false,
  "canRemoveTagUsages": false,
  "commentCount": 0,
  "createDate": "2021-11-10T05:17:12.943",
  "deleted": false,
  "hits": 6182,
  "latestComments": [],
  "likeCount": 74,
  "listCount": 152,
  "lyricsFromParents": [
    {
      "cultureCodes": ["ja"],
      "id": 95304,
      "source": "YouTube",
      "translationType": "Original",
      "url": "https://www.youtube.com/watch?v=3sEptl-psU0"
    },
    {
      "cultureCodes": [""],
      "id": 95362,
      "source": "Vocaloid Lyrics Wiki",
      "translationType": "Romanized",
      "url": "https://vocaloidlyrics.fandom.com/wiki/ロウワー_(Lower)"
    },
    {
      "cultureCodes": ["en"],
      "id": 96251,
      "source": "Pupleon",
      "translationType": "Translation",
      "url": "https://vocaloidlyrics.fandom.com/wiki/%E3%83%AD%E3%82%A6%E3%83%AF%E3%83%BC_(Lower)?so=search"
    },
    {
      "cultureCodes": ["en"],
      "id": 163733,
      "source": "Oktavia",
      "translationType": "Translation",
      "url": "https://sonimiki.tumblr.com/post/711404322120925185/bt-lower-ones-eyes%E3%83%AD%E3%82%A6%E3%83%AF%E3%83%BC"
    },
    {
      "cultureCodes": ["pt"],
      "id": 163734,
      "source": "DinoKun",
      "translationType": "Translation",
      "url": "https://youtu.be/IpWEdhNZre8"
    },
    {
      "cultureCodes": ["es"],
      "id": 163735,
      "source": "shokura",
      "translationType": "Translation",
      "url": "https://cloverknight.dreamwidth.org/4270.html"
    }
  ],
  "maxMilliBpm": 132000,
  "minMilliBpm": 132000,
  "notes": {
    "english": "\"Project SEKAI COLORFUL STAGE! feat. Hatsune Miku\"\n\"[Nightcord at 25:00](https://vocadb.net/Ar/83861)\" Newly-written Song\n\n- Release date: Date of song addition to Project SEKAI.",
    "original": "『プロジェクトセカイ カラフルステージ！ feat. 初音ミク』\n『[25時、ナイトコードで。](https://vocadb.net/Ar/83861)』書き下ろし楽曲\n\n- Release date: Date of song addition to Project SEKAI."
  },
  "pools": [
    { "featuredCategory": "Pools", "id": 30, "name": "(NND) More than 1 000 000 views" },
    { "featuredCategory": "Pools", "id": 6478, "name": "(YT) More than 10 000 000 views" },
    {
      "featuredCategory": "Pools",
      "id": 9375,
      "name": "Game: Project SEKAI COLORFUL STAGE! feat. Hatsune Miku (Original Songs)"
    }
  ],
  "preferredLyrics": {
    "cultureCodes": ["en"],
    "id": 96251,
    "source": "Pupleon",
    "translationType": "Translation",
    "url": "https://vocaloidlyrics.fandom.com/wiki/%E3%83%AD%E3%82%A6%E3%83%AF%E3%83%BC_(Lower)?so=search"
  },
  "pvs": [
    {
      "author": "ぬゆり",
      "disabled": false,
      "id": 544526,
      "length": 230,
      "name": "ロウワ― / Flower",
      "publishDate": "2021-11-11T00:00:00",
      "pvId": "sm39608927",
      "service": "NicoNicoDouga",
      "pvType": "Original",
      "thumbUrl": "https://nicovideo.cdn.nimg.jp/thumbnails/39608927/39608927.7527358",
      "url": "http://www.nicovideo.jp/watch/sm39608927"
    },
    {
      "author": "Lanndo / nulut Official",
      "disabled": false,
      "id": 544527,
      "length": 230,
      "name": "ロウワ― / Flower",
      "publishDate": "2021-11-11T00:00:00",
      "pvId": "3sEptl-psU0",
      "service": "Youtube",
      "pvType": "Original",
      "thumbUrl": "https://i.ytimg.com/vi/3sEptl-psU0/default.jpg",
      "url": "https://youtu.be/3sEptl-psU0"
    },
    {
      "author": "ぬゆり - Topic",
      "disabled": false,
      "id": 544528,
      "length": 230,
      "name": "ロウワー",
      "publishDate": "2021-11-09T00:00:00",
      "pvId": "dWBYKVvgZ5s",
      "service": "Youtube",
      "pvType": "Original",
      "thumbUrl": "https://i.ytimg.com/vi/dWBYKVvgZ5s/default.jpg",
      "url": "https://youtu.be/dWBYKVvgZ5s"
    },
    {
      "author": "nulut",
      "disabled": false,
      "extendedMetadata": {
        "json": "{\"Aid\":806550440,\"Bvid\":\"BV1V34y1Z7Ae\",\"Cid\":440400082}"
      },
      "id": 697306,
      "length": 231,
      "name": "ロウワ― / Flower -lower one's eyes",
      "publishDate": "2021-11-11T00:00:00",
      "pvId": "806550440",
      "service": "Bilibili",
      "pvType": "Original",
      "thumbUrl": "http://i1.hdslb.com/bfs/archive/d4a33930f3b998a54351f39f5e69f919fc08c6c4.jpg",
      "url": "https://www.bilibili.com/video/av806550440"
    },
    {
      "author": "ぬゆり - Topic",
      "disabled": false,
      "id": 1019248,
      "length": 230,
      "name": "Lower",
      "publishDate": "2023-03-09T00:00:00",
      "pvId": "gOkV2TQioTQ",
      "service": "Youtube",
      "pvType": "Original",
      "thumbUrl": "https://i.ytimg.com/vi/gOkV2TQioTQ/default.jpg",
      "url": "https://youtu.be/gOkV2TQioTQ"
    },
    {
      "author": "ぬゆり - Topic",
      "disabled": false,
      "id": 1019249,
      "length": 230,
      "name": "ロウワー",
      "publishDate": "2023-03-09T00:00:00",
      "pvId": "SNAFSFerjko",
      "service": "Youtube",
      "pvType": "Original",
      "thumbUrl": "https://i.ytimg.com/vi/SNAFSFerjko/default.jpg",
      "url": "https://youtu.be/SNAFSFerjko"
    }
  ],
  "releaseEvents": [],
  "song": {
    "artistString": "ぬゆり feat. v4 flower",
    "createDate": "2021-11-10T05:17:12.943",
    "defaultName": "ロウワー",
    "defaultNameLanguage": "Japanese",
    "favoritedTimes": 71,
    "id": 365108,
    "lengthSeconds": 230,
    "mainPicture": {
      "urlOriginal": "https://i1.ytimg.com/vi/3sEptl-psU0/hqdefault.jpg",
      "urlThumb": "https://nicovideo.cdn.nimg.jp/thumbnails/39608927/39608927.7527358"
    },
    "name": "ロウワー",
    "publishDate": "2021-10-31T00:00:00Z",
    "pvServices": "NicoNicoDouga, Youtube, Bilibili",
    "ratingScore": 361,
    "songType": "Original",
    "status": "Finished",
    "version": 29
  },
  "songTypeTag": { "id": 6479, "name": "original song", "urlSlug": "original-song" },
  "subjectsFromParents": [],
  "suggestions": [
    {
      "additionalNames": "World's End Dancehall, 世末舞厅, 世界末日舞厅",
      "artistString": "wowaka feat. 初音ミク, 巡音ルカ",
      "createDate": "2011-01-12T18:26:18",
      "defaultName": "ワールズエンド・ダンスホール",
      "defaultNameLanguage": "Japanese",
      "favoritedTimes": 281,
      "id": 20,
      "lengthSeconds": 218,
      "mainPicture": {
        "urlOriginal": "https://i1.ytimg.com/vi/ZB75e7vzX0I/hqdefault.jpg",
        "urlThumb": "https://nicovideo.cdn.nimg.jp/thumbnails/10759623/10759623"
      },
      "name": "ワールズエンド・ダンスホール",
      "publishDate": "2010-05-18T00:00:00Z",
      "pvServices": "NicoNicoDouga, Youtube",
      "ratingScore": 1357,
      "songType": "Original",
      "status": "Approved",
      "version": 30
    },
    {
      "additionalNames": "Rollin' Girl, Rolling Girl, 翻滚少女",
      "artistString": "wowaka feat. 初音ミク",
      "createDate": "2011-11-01T22:10:01",
      "defaultName": "ローリンガール",
      "defaultNameLanguage": "Japanese",
      "favoritedTimes": 462,
      "id": 1501,
      "lengthSeconds": 196,
      "mainPicture": {
        "urlOriginal": "https://i1.ytimg.com/vi/vnw8zURAxkU/hqdefault.jpg",
        "urlThumb": "http://nicovideo.cdn.nimg.jp/thumbnails/9714351/9714351"
      },
      "name": "ローリンガール",
      "publishDate": "2010-02-14T00:00:00Z",
      "pvServices": "NicoNicoDouga, Youtube, SoundCloud",
      "ratingScore": 2130,
      "songType": "Original",
      "status": "Approved",
      "version": 31
    },
    {
      "additionalNames": "Arifureta Sekai Seifuku, Common World Domination",
      "artistString": "ピノキオピー feat. 初音ミク Append (Dark)",
      "createDate": "2012-06-18T19:49:47",
      "defaultName": "ありふれたせかいせいふく",
      "defaultNameLanguage": "Japanese",
      "favoritedTimes": 206,
      "id": 13351,
      "lengthSeconds": 205,
      "mainPicture": {
        "urlOriginal": "https://i1.ytimg.com/vi/8Z3TbMBfDM0/hqdefault.jpg",
        "urlThumb": "https://i.ytimg.com/vi/8Z3TbMBfDM0/default.jpg"
      },
      "name": "ありふれたせかいせいふく",
      "publishDate": "2012-06-18T00:00:00Z",
      "pvServices": "NicoNicoDouga, Youtube",
      "ratingScore": 1064,
      "songType": "Original",
      "status": "Approved",
      "version": 25
    },
    {
      "additionalNames": "Lost One no Goukoku, Lost One's Weeping, The Lamentations of the Lost Ones, 로스트원의 호곡",
      "artistString": "Neru feat. 鏡音リン Append (Power)",
      "createDate": "2012-12-21T17:47:14",
      "defaultName": "ロストワンの号哭",
      "defaultNameLanguage": "Japanese",
      "favoritedTimes": 320,
      "id": 19094,
      "lengthSeconds": 217,
      "mainPicture": {
        "urlOriginal": "https://i1.ytimg.com/vi/8oBV3jPTW4s/hqdefault.jpg",
        "urlThumb": "https://nicovideo.cdn.nimg.jp/thumbnails/20244918/20244918"
      },
      "name": "ロストワンの号哭",
      "publishDate": "2013-03-04T00:00:00Z",
      "pvServices": "NicoNicoDouga, Youtube",
      "ratingScore": 1532,
      "songType": "Original",
      "status": "Approved",
      "version": 25
    }
  ],
  "tags": [
    {
      "count": 8,
      "tag": {
        "additionalNames": "ProSeka, プロジェクトセカイ カラフルステージ！ feat. 初音ミク, Project SEKAI COLORFUL STAGE! feat. Hatsune Miku, HATSUNE MIKU: COLORFUL STAGE!, 世界計畫 繽紛舞台！feat. 初音未來, Colorful Stage, 프로젝트 세카이 컬러풀 스테이지! feat.하츠네 미쿠, 프로세카",
        "categoryName": "Games",
        "id": 7323,
        "name": "プロセカ",
        "urlSlug": "proseka"
      }
    },
    {
      "count": 7,
      "tag": {
        "additionalNames": "yuri, ガールズラブ, girls' love, lesbian, shoujo-ai, ゆり, GL, sapphic",
        "categoryName": "Themes",
        "id": 493,
        "name": "百合",
        "urlSlug": "yuri"
      }
    },
    {
      "count": 7,
      "tag": {
        "additionalNames": "エレクトロスウィング, エレクトロスイング, electroswing, electric swing, 电子摇摆",
        "categoryName": "Genres",
        "id": 3373,
        "name": "electro swing",
        "urlSlug": "electro-swing"
      }
    },
    {
      "count": 7,
      "tag": {
        "additionalNames": "宗教, religious, 宗教音楽, christianity, islam, hinduism, judaism, taoism, jesus christ, jesus of nazareth",
        "categoryName": "Themes",
        "id": 3409,
        "name": "religion",
        "urlSlug": "religion"
      }
    },
    {
      "count": 7,
      "tag": {
        "additionalNames": "ウイッチ, ウイッチクラフト, witchcraft, 魔女, spellcraft",
        "categoryName": "Themes",
        "id": 4973,
        "name": "witch",
        "urlSlug": "witch"
      }
    },
    {
      "count": 6,
      "tag": {
        "additionalNames": "お洒落, fashionable, おしゃれ",
        "categoryName": "Subjective",
        "id": 3015,
        "name": "stylish",
        "urlSlug": "stylish"
      }
    },
    {
      "count": 6,
      "tag": {
        "additionalNames": "GLBT, LGBTQIA2S+, LGBT, queer, bisexual, LGB, non-heterosexual, non-cisgender, gay, homosexual",
        "categoryName": "Themes",
        "id": 7025,
        "name": "LGBTQ+",
        "urlSlug": "lgbtq"
      }
    },
    {
      "count": 6,
      "tag": {
        "additionalNames": "裏切り",
        "categoryName": "Themes",
        "id": 7081,
        "name": "betrayal",
        "urlSlug": "betrayal"
      }
    },
    {
      "count": 5,
      "tag": {
        "additionalNames": "2DアニメーションPV, 2D PV",
        "categoryName": "Animation",
        "id": 3287,
        "name": "2D animated PV",
        "urlSlug": "2d-animated-pv"
      }
    },
    {
      "count": 4,
      "tag": {
        "additionalNames": "visual novel soundtrack",
        "categoryName": "Sources",
        "id": 456,
        "name": "video game soundtrack",
        "urlSlug": "video-game-soundtrack"
      }
    },
    {
      "count": 4,
      "tag": {
        "additionalNames": "愛, 恋, 恋愛, romance, ロマンチック・ラブ, romantic love, ラブ, ラブソング, love song",
        "categoryName": "Themes",
        "id": 1569,
        "name": "love",
        "urlSlug": "love"
      }
    },
    {
      "count": 4,
      "tag": {
        "additionalNames": "カラオケ配布, off vocal available, instrumental available, インストルメンタル配布, off-vocal available, インスト配布, inst配布, オフボ配布, オフボーカル配布",
        "categoryName": "Distribution",
        "id": 3113,
        "name": "karaoke available",
        "urlSlug": "karaoke-available"
      }
    },
    {
      "count": 4,
      "tag": {
        "additionalNames": "lively, hyper",
        "categoryName": "Subjective",
        "id": 9001,
        "name": "energetic",
        "urlSlug": "energetic"
      }
    },
    {
      "count": 3,
      "tag": {
        "additionalNames": "切ない, sadness, 悲しみ",
        "categoryName": "Subjective",
        "id": 384,
        "name": "sad",
        "urlSlug": "sad"
      }
    },
    {
      "count": 3,
      "tag": {
        "additionalNames": "デジタルロック, エレクトロ ロック, electro-rock, electrorock, electronic rock, synth rock, synthrock, technorock",
        "categoryName": "Genres",
        "id": 2878,
        "name": "digital rock",
        "urlSlug": "digital-rock"
      }
    },
    {
      "count": 3,
      "tag": {
        "additionalNames": "暗い, ダーク",
        "categoryName": "Themes",
        "id": 2957,
        "name": "dark",
        "urlSlug": "dark"
      }
    },
    {
      "count": 3,
      "tag": {
        "additionalNames": "オルタナティブダンス, indie dance",
        "categoryName": "Genres",
        "id": 4646,
        "name": "alternative dance",
        "urlSlug": "alternative-dance"
      }
    },
    {
      "count": 3,
      "tag": {
        "additionalNames": "同時投稿, カテゴリ並行うｐ",
        "categoryName": "Editor notes",
        "id": 4946,
        "name": "simultaneous upload",
        "urlSlug": "simultaneous-upload"
      }
    },
    {
      "count": 3,
      "tag": {
        "additionalNames": "花, 華, flowers",
        "categoryName": "Themes",
        "id": 6151,
        "name": "flower",
        "urlSlug": "flower"
      }
    },
    {
      "count": 3,
      "tag": {
        "additionalNames": "メイド, housemaid, maidservant, maid-servant",
        "categoryName": "Themes",
        "id": 6833,
        "name": "maid",
        "urlSlug": "maid"
      }
    },
    {
      "count": 3,
      "tag": {
        "additionalNames": "文学",
        "categoryName": "Themes",
        "id": 7339,
        "name": "literature",
        "urlSlug": "literature"
      }
    },
    {
      "count": 3,
      "tag": {
        "additionalNames": "DAM&JOY配信中",
        "categoryName": "Distribution",
        "id": 8087,
        "name": "karaoke available (DAM&JOY)",
        "urlSlug": "karaoke-available-damjoy"
      }
    },
    {
      "count": 3,
      "tag": {
        "additionalNames": "ダンスPV, 踊ってみた, odottemita",
        "categoryName": "Animation",
        "id": 8422,
        "name": "dance PV",
        "urlSlug": "dance-pv"
      }
    },
    {
      "count": 2,
      "tag": {
        "additionalNames": "ピンク, magenta, マゼンタ, rose (color), 薔薇色, 桜色",
        "categoryName": "Themes",
        "id": 6550,
        "name": "pink",
        "urlSlug": "pink"
      }
    },
    {
      "count": 2,
      "tag": {
        "additionalNames": "泣き, naki, tears, weeping, 泣く",
        "categoryName": "Themes",
        "id": 8554,
        "name": "crying",
        "urlSlug": "crying"
      }
    },
    {
      "count": 2,
      "tag": {
        "additionalNames": "黄色, kiiro, gold (color), goldenrod, gold",
        "categoryName": "Themes",
        "id": 8915,
        "name": "yellow",
        "urlSlug": "yellow"
      }
    },
    {
      "count": 1,
      "tag": {
        "additionalNames": "死",
        "categoryName": "Themes",
        "id": 2821,
        "name": "death",
        "urlSlug": "death"
      }
    },
    {
      "count": 1,
      "tag": {
        "additionalNames": "ゴシック, ゴス, goth",
        "categoryName": "Themes",
        "id": 3062,
        "name": "gothic",
        "urlSlug": "gothic"
      }
    },
    {
      "count": 1,
      "tag": {
        "additionalNames": "火",
        "categoryName": "Themes",
        "id": 6904,
        "name": "fire",
        "urlSlug": "fire"
      }
    },
    {
      "count": 1,
      "tag": {
        "additionalNames": "region-blocked, region-locked",
        "categoryName": "Distribution",
        "id": 8226,
        "name": "region blocked",
        "urlSlug": "region-blocked"
      }
    }
  ],
  "userRating": "Nothing",
  "webLinks": [
    {
      "category": "Reference",
      "description": "25時、ナイトコードで。ver.",
      "disabled": false,
      "id": 115542,
      "url": "https://vocadb.net/S/365111"
    },
    {
      "category": "Reference",
      "description": "UtaiteDB",
      "disabled": false,
      "id": 154963,
      "url": "https://utaitedb.net/S/51202"
    }
  ],
  "cultureCodes": ["ja"]
}
